jax_moseq/__init__.py
jax_moseq/models/__init__.py
jax_moseq/models/arhmm/__init__.py
jax_moseq/models/arhmm/generate.py
jax_moseq/models/arhmm/gibbs.py
jax_moseq/models/arhmm/initialize.py
jax_moseq/models/arhmm/log_prob.py
jax_moseq/models/keypoint_slds/__init__.py
jax_moseq/models/keypoint_slds/alignment.py
jax_moseq/models/keypoint_slds/gibbs.py
jax_moseq/models/keypoint_slds/initialize.py
jax_moseq/models/keypoint_slds/log_prob.py
jax_moseq/models/slds/__init__.py
jax_moseq/models/slds/gibbs.py
jax_moseq/models/slds/initialize.py
jax_moseq/models/slds/log_prob.py
jax_moseq/utils/__init__.py
jax_moseq/utils/autoregression.py
jax_moseq/utils/distributions.py
jax_moseq/utils/kalman.py
jax_moseq/utils/transitions.py
jax_moseq/utils/utils.py
jax_moseq-0.0.1.dist-info/LICENSE.md
jax_moseq-0.0.1.dist-info/METADATA
jax_moseq-0.0.1.dist-info/WHEEL
jax_moseq-0.0.1.dist-info/top_level.txt
jax_moseq-0.0.1.dist-info/RECORD
