Metadata-Version: 2.1
Name: jax-moseq
Version: 0.0.1
Home-page: https://github.com/dattalab/jax-moseq/tree/0.0.0
Download-URL: https://github.com/dattalab/jax-moseq/archive/refs/tags/0.0.0.tar.gz
Author: Caleb Weinreb
Author-email: calebsw@gmail.com
Classifier: Programming Language :: Python :: 3
Classifier: Operating System :: OS Independent
Requires-Python: >=3.8
License-File: LICENSE.md
Requires-Dist: numba
Requires-Dist: dynamax
Requires-Dist: chex (==0.1.6)
Requires-Dist: tqdm
